killbill_xml_builder/__init__.py
killbill_xml_builder/base.py
killbill_xml_builder/enums.py
killbill_xml_builder/builders/__init__.py
killbill_xml_builder/builders/catalogs.py
killbill_xml_builder/builders/currencies.py
killbill_xml_builder/builders/phases.py
killbill_xml_builder/builders/plans.py
killbill_xml_builder/builders/prices.py
killbill_xml_builder/builders/products.py
killbill_xml_builder/builders/rules.py
killbill_xml_builder/utils/__init__.py
killbill_xml_builder-0.1.0.dist-info/METADATA
killbill_xml_builder-0.1.0.dist-info/WHEEL
killbill_xml_builder-0.1.0.dist-info/licenses/LICENSE
killbill_xml_builder-0.1.0.dist-info/RECORD
