Metadata-Version: 2.4
Name: killbill-xml-builder
Version: 0.1.0
Summary: killbill xml builder
Project-URL: Homepage, https://github.com/raulodev/killbill-xml-builder
Project-URL: Issues, https://github.com/raulodev/killbill-xml-builder/issues
Author-email: Raul Cobiellas <raulodev@gmail.com>
License-File: LICENSE
Keywords: bill,kill,killbill,xml
Classifier: License :: OSI Approved :: MIT License
Classifier: Operating System :: OS Independent
Classifier: Programming Language :: Python :: 3
Requires-Python: >=3.8
